Example-b8-5/Source/counter.v
module counter (count, clk, reset);
output [7:0] count;
input clk, reset;

reg [7:0] count;
parameter tpd_clk_to_count   =  1;
parameter tpd_reset_to_count =  1;


function [7:0] increment;
input [7:0] val;
reg [3:0] i;
reg carry;
  begin
    increment = val;
    carry = 1'b1;
    /* 
     * Exit this loop when carry == zero, OR all bits processed 
     */ 
    for (i = 4'b0; ((carry == 4'b1) || (i <= 7));  i = i+ 4'b1)
       begin
         increment[i] = val[i] ^ carry;
         carry = val[i] & carry;
       end
  end       
endfunction

always @ (posedge clk or posedge reset)
  if (reset)
     count = #tpd_reset_to_count 8'h00;
  else
     count <= #tpd_clk_to_count increment(count);

/*
 * To make module counter synthesizeable, use the following
 *  alternate form of the always block:
 */
/***********************************************
always @ (posedge clk or posedge reset)
  if (reset)
     count <= 8'h00;
  else
     count <= count + 8'h01;
***********************************************/

endmodule

Example-b8-5/Source/tcounter.v
module test_counter;

reg clk, rst;
wire [7:0] count;

counter #(5,10) dut (count,clk,rst);

initial // Clock generator
  begin
    clk = 0;
    #10 forever #10 clk = !clk;
  end
  
initial	// Test stimulus
  begin
    rst = 0;
    #5 rst = 1;
    #4 rst = 0;
    #50000 $stop;
  end
  
initial
    $monitor($stime,, rst,, clk,,, count); 
    
endmodule

Example-b8-5/demo_project/myvcdfile.vcd
$date
	Sun Nov 10 15:28:00 2002
$end
$version
	ModelSim Version 5.5f
$end
$timescale
	1ns
$end
$scope module test_counter $end
$scope module dut $end
$var parameter 32 ! tpd_clk_to_count $end
$var parameter 32 " tpd_reset_to_count $end
$var reg 8 # count [7:0] $end
$var wire 1 $ clk $end
$var wire 1 % reset $end
$upscope $end
$upscope $end
$enddefinitions $end
#0
$dumpvars
b101 !
b1010 "
bx #
0$
0%
$end
#5
1%
#9
0%
#15
b0 #
#20
1$
#25
b1 #
#30
0$
#40
1$
#45
b10 #
#50
0$
#60
1$
#65
b11 #
#70
0$
#80
1$
#85
b100 #
